palonso_sales/sales.py
palonso_sales/settings.py
palonso_sales-0.0.1.dist-info/METADATA
palonso_sales-0.0.1.dist-info/WHEEL
palonso_sales-0.0.1.dist-info/RECORD
